[
  {
    "name": "T- Shirt",
    "description": "A comfortable wear which gives you premium feel",
    "price": 1233,
    "category": "Clothing",
    "imageUrl": "https://res.cloudinary.com/local-ite/image/upload/v1761794783/ecommerce-products/Tshirt_qre2vg.webp",
    "rating": 4.2,
    "stock": 53,
    "id": "1761794920576-2ob5stgxd",
    "slug": "t-shirt",
    "createdAt": "2025-10-30T03:28:40.577Z",
    "updatedAt": "2025-10-30T03:28:40.577Z"
  },
  {
    "name": "T-Shirt",
    "description": "A Good wear to make you feel nice",
    "price": 499,
    "category": "Clothing",
    "imageUrl": "https://res.cloudinary.com/local-ite/image/upload/v1761795129/ecommerce-products/Tshirt2_daenmm.webp",
    "rating": 3.9,
    "stock": 32,
    "id": "1761795264184-4948qnhrs",
    "slug": "t-shirt",
    "createdAt": "2025-10-30T03:34:24.184Z",
    "updatedAt": "2025-10-30T03:34:24.184Z"
  },
  {
    "name": "Asus RTX509",
    "description": "A powerfull Asus laptop build for heavy gaming and video editing",
    "price": 68999,
    "category": "Electronics",
    "imageUrl": "https://res.cloudinary.com/local-ite/image/upload/v1761795671/ecommerce-products/laptop_hak900.webp",
    "rating": 4.4,
    "stock": 16,
    "id": "1761795846176-w1bkxvlly",
    "slug": "asus-rtx509",
    "createdAt": "2025-10-30T03:44:06.176Z",
    "updatedAt": "2025-10-30T03:44:06.177Z"
  },
  {
    "name": "MSI GE78 HX - High-end gaming series",
    "description": "Professional gamers/esports athletes.\nVideo editors/3D animators working with 8K footage\n\n",
    "price": 608600,
    "category": "Electronics",
    "imageUrl": "https://res.cloudinary.com/local-ite/image/upload/v1761795855/ecommerce-products/MSi_hjac1m.webp",
    "rating": 4.8,
    "stock": 8,
    "id": "1761796141191-ek0ats07x",
    "slug": "msi-ge78-hx-high-end-gaming-series",
    "createdAt": "2025-10-30T03:49:01.191Z",
    "updatedAt": "2025-10-30T03:49:01.191Z"
  },
  {
    "name": "DSC -Bats",
    "description": "A light weight high quality DSC product",
    "price": 1320,
    "category": "Sports",
    "imageUrl": "https://res.cloudinary.com/local-ite/image/upload/v1761796134/ecommerce-products/BAts_ourtwr.webp",
    "rating": 3.6,
    "stock": 136,
    "id": "1761796261556-40k0tk98w",
    "slug": "dsc-bats",
    "createdAt": "2025-10-30T03:51:01.556Z",
    "updatedAt": "2025-10-30T03:51:01.556Z"
  },
  {
    "name": "Yonex ",
    "description": "A light weight high quality racket",
    "price": 2679,
    "category": "Sports",
    "imageUrl": "https://res.cloudinary.com/local-ite/image/upload/v1761796199/ecommerce-products/Racket_vucehi.webp",
    "rating": 4.6,
    "stock": 67,
    "id": "1761796352872-xpf3tsraj",
    "slug": "yonex-",
    "createdAt": "2025-10-30T03:52:32.872Z",
    "updatedAt": "2025-10-30T03:52:32.872Z"
  },
  {
    "name": "Decoratives",
    "description": "A beautliful decorative piece which will enhance your home .",
    "price": 2648,
    "category": "Home & Garden",
    "imageUrl": "https://res.cloudinary.com/local-ite/image/upload/v1761796290/ecommerce-products/Home_ozvq1p.jpg",
    "rating": 3.9,
    "stock": 30,
    "id": "1761796432231-amewbuzbp",
    "slug": "decoratives",
    "createdAt": "2025-10-30T03:53:52.231Z",
    "updatedAt": "2025-10-30T03:53:52.231Z"
  },
  {
    "name": "Toy - Helicopter",
    "description": "A remote control toy helicopter made for kids .",
    "price": 462,
    "category": "Toys",
    "imageUrl": "https://res.cloudinary.com/local-ite/image/upload/v1761796369/ecommerce-products/Helioc_ubdoum.webp",
    "rating": 3.6,
    "stock": 56,
    "id": "1761796498720-gdy1wj8ox",
    "slug": "toy-helicopter",
    "createdAt": "2025-10-30T03:54:58.720Z",
    "updatedAt": "2025-10-30T03:54:58.720Z"
  },
  {
    "name": "Lamborghini ",
    "description": "A high speed toy Lamborghini",
    "price": 699,
    "category": "Toys",
    "imageUrl": "https://res.cloudinary.com/local-ite/image/upload/v1761796434/ecommerce-products/REmote_jyuw7v.webp",
    "rating": 4.2,
    "stock": 23,
    "id": "1761796560724-ibpp2j35a",
    "slug": "lamborghini-",
    "createdAt": "2025-10-30T03:56:00.724Z",
    "updatedAt": "2025-10-30T03:56:00.724Z"
  },
  {
    "name": "Book -Dopamine Detox",
    "description": "A book you must read to know how to detox dopamine",
    "price": 360,
    "category": "Books",
    "imageUrl": "https://res.cloudinary.com/local-ite/image/upload/v1761796632/ecommerce-products/books_ckbmxc.webp",
    "rating": 4,
    "stock": 62,
    "id": "1761796794861-joqt06s79",
    "slug": "book-dopamine-detox",
    "createdAt": "2025-10-30T03:59:54.861Z",
    "updatedAt": "2025-10-30T03:59:54.861Z"
  },
  {
    "name": "How to Spend money",
    "description": "Know where to and how to spend money.",
    "price": 899,
    "category": "Books",
    "imageUrl": "https://res.cloudinary.com/local-ite/image/upload/v1761796730/ecommerce-products/books2_kpk2ga.webp",
    "rating": 4.6,
    "stock": 60,
    "id": "1761796865073-4xb111xr5",
    "slug": "how-to-spend-money",
    "createdAt": "2025-10-30T04:01:05.073Z",
    "updatedAt": "2025-10-30T04:01:05.073Z"
  },
  {
    "name": "iPhone 17 Pro Max 1 TB: 17.42 cm (6.9″) Diplay",
    "description": "Display with Promotion, A19 Pro Chip, Best Battery Life in Any iPhone Ever, Pro Fusion Camera System, Center Stage Front Camera; Silver",
    "price": 189900,
    "category": "Electronics",
    "imageUrl": "https://res.cloudinary.com/local-ite/image/upload/v1761796912/ecommerce-products/iphone_hfwhlj.webp",
    "rating": 4.7,
    "stock": 39,
    "id": "1761797093372-i1lr73yr0",
    "slug": "iphone-17-pro-max-1-tb-1742-cm-69-diplay",
    "createdAt": "2025-10-30T04:04:53.383Z",
    "updatedAt": "2025-10-30T04:04:53.383Z"
  }
]